Metadata-Version: 1.0
Name: GxCsvToJson
Version: 1.0.5
Summary: Convert Csv to Json
Home-page: UNKNOWN
Author: zhaobk
Author-email: zhaobk@nationalchip.com
License: UNKNOWN
Keywords: json csv
Platform: UNKNOWN
